mbe_mcp_server/__init__.py
mbe_mcp_server/main.py
mbe_mcp_server-0.1.6.dist-info/METADATA
mbe_mcp_server-0.1.6.dist-info/WHEEL
mbe_mcp_server-0.1.6.dist-info/entry_points.txt
mbe_mcp_server-0.1.6.dist-info/top_level.txt
mbe_mcp_server-0.1.6.dist-info/RECORD
