Metadata-Version: 2.4
Name: mbe_mcp_server
Version: 0.1.6
Summary: 韬略服务对外Mcp服务
Home-page: 
Author: yanan.wya
Author-email: wya0556@qq.com
Classifier: Programming Language :: Python :: 3
Classifier: Operating System :: OS Independent
Requires-Python: >=3.6
Requires-Dist: mcp
Dynamic: author
Dynamic: author-email
Dynamic: classifier
Dynamic: description
Dynamic: requires-dist
Dynamic: requires-python
Dynamic: summary
